ImageToColors/ImageToColors.py
ImageToColors/__init__.py
ImageToColors/test.py
ImageToColors-1.1.dist-info/LICENSE.txt
ImageToColors-1.1.dist-info/METADATA
ImageToColors-1.1.dist-info/WHEEL
ImageToColors-1.1.dist-info/top_level.txt
ImageToColors-1.1.dist-info/RECORD
