Metadata-Version: 2.1
Name: ImageToColors
Version: 1.1
Summary: Image color clustering library for extracting N dominant colors from image
Home-page: https://github.com/MayurSatav/ImageToColors
Author: Mayur Satav
Author-email: mayursatav9@gmail.com
License: UNKNOWN
Platform: UNKNOWN
Classifier: Programming Language :: Python :: 3
Classifier: License :: OSI Approved :: MIT License
Classifier: Operating System :: OS Independent
